Metadata-Version: 1.0
Name: git-rename-authors
Version: 0.1.0
Summary: GUI to clean git repository authors
Home-page: https://github.com/guillaumevincent/git-rename-authors
Author: Guillaume Vincent
Author-email: guillaume@oslab.fr
License: MIT
Platform: UNKNOWN
